django_push_dispatcher-0.1.7.dist-info/licenses/LICENSE
push_dispatcher/__init__.py
push_dispatcher/firebase_utils.py
push_dispatcher/notifications.py
push_dispatcher/utils.py
django_push_dispatcher-0.1.7.dist-info/METADATA
django_push_dispatcher-0.1.7.dist-info/WHEEL
django_push_dispatcher-0.1.7.dist-info/top_level.txt
django_push_dispatcher-0.1.7.dist-info/RECORD
